international/__init__.py
international/admin.py
international/apps.py
international/localize.py
international/middleware.py
international/models.py
international/tests.py
international/urls.py
international/views.py
international/management/commands/check_and_update_geoip2.py
international/management/commands/__pycache__/check_and_update_geoip2.cpython-37.pyc
international/migrations/0001_initial.py
international/migrations/0002_alter_countrysite_country_code.py
international/migrations/0003_alter_countrysite_default_language.py
international/migrations/0004_countrysite_icon.py
international/migrations/0005_auto_20210906_1542.py
international/migrations/0006_countrysite_active.py
international/migrations/__init__.py
international/sitemaps/__init__.py
international/sitemaps/views.py
django_international_sites-0.1.10.dist-info/LICENSE
django_international_sites-0.1.10.dist-info/METADATA
django_international_sites-0.1.10.dist-info/WHEEL
django_international_sites-0.1.10.dist-info/top_level.txt
django_international_sites-0.1.10.dist-info/RECORD
