Metadata-Version: 2.1
Name: django-international-sites
Version: 0.1.10
Summary: Django app to serve multiple sites/countries/domains from a single application
Home-page: https://github.com/project-cece/django-international-sites
Author: Marcella Wijngaarden
Author-email: marcellawijngaarden@hotmail.com
License: MIT License
Platform: UNKNOWN
Classifier: Development Status :: 3 - Alpha
Classifier: Environment :: Web Environment
Classifier: Intended Audience :: Developers
Classifier: Framework :: Django
Classifier: Framework :: Django :: 3.0
Classifier: Operating System :: OS Independent
Classifier: License :: OSI Approved :: MIT License
Classifier: Programming Language :: Python :: 3.6
Classifier: Programming Language :: Python :: 3.7
Classifier: Programming Language :: Python :: 3.8
Requires-Python: >=3.6
Requires-Dist: Django (>=3.0)
Requires-Dist: geoip2 (>=4.2.0)
